tibiawikisql/__init__.py
tibiawikisql/__main__.py
tibiawikisql/api.py
tibiawikisql/database.py
tibiawikisql/errors.py
tibiawikisql/generation.py
tibiawikisql/schema.py
tibiawikisql/server.py
tibiawikisql/utils.py
tibiawikisql/models/__init__.py
tibiawikisql/models/achievement.py
tibiawikisql/models/base.py
tibiawikisql/models/charm.py
tibiawikisql/models/creature.py
tibiawikisql/models/house.py
tibiawikisql/models/imbuement.py
tibiawikisql/models/item.py
tibiawikisql/models/mount.py
tibiawikisql/models/npc.py
tibiawikisql/models/outfit.py
tibiawikisql/models/quest.py
tibiawikisql/models/spell.py
tibiawikisql/models/update.py
tibiawikisql/models/world.py
tibiawikisql/parsers/__init__.py
tibiawikisql/parsers/achievement.py
tibiawikisql/parsers/base.py
tibiawikisql/parsers/book.py
tibiawikisql/parsers/charm.py
tibiawikisql/parsers/creature.py
tibiawikisql/parsers/house.py
tibiawikisql/parsers/imbuement.py
tibiawikisql/parsers/item.py
tibiawikisql/parsers/key.py
tibiawikisql/parsers/mount.py
tibiawikisql/parsers/npc.py
tibiawikisql/parsers/outfit.py
tibiawikisql/parsers/quest.py
tibiawikisql/parsers/spell.py
tibiawikisql/parsers/update.py
tibiawikisql/parsers/world.py
tibiawikisql-7.0.3.dist-info/licenses/LICENSE
tibiawikisql-7.0.3.dist-info/METADATA
tibiawikisql-7.0.3.dist-info/WHEEL
tibiawikisql-7.0.3.dist-info/entry_points.txt
tibiawikisql-7.0.3.dist-info/top_level.txt
tibiawikisql-7.0.3.dist-info/RECORD
