Metadata-Version: 2.4
Name: tibiawikisql
Version: 7.0.3
Summary: Python script that generates a SQLite database from TibiaWiki articles
Author-email: Allan Galarza <allan.galarza@gmail.com>
Maintainer-email: Allan Galarza <allan.galarza@gmail.com>
License: Apache 2.0
Project-URL: Homepage, https://tibiawiki-sql.readthedocs.io/
Project-URL: Documentation, https://tibiawiki-sql.readthedocs.io/
Project-URL: Repository, https://github.com/Galarzaa90/tibiawiki-sql
Project-URL: Changelog, https://tibiawiki-sql.readthedocs.io/en/stable/changelog/
Project-URL: Docker Hub: Repo, https://hub.docker.com/repository/docker/galarzaa90/tibiawiki-sql
Classifier: Development Status :: 5 - Production/Stable
Classifier: Environment :: Console
Classifier: Intended Audience :: Developers
Classifier: License :: OSI Approved :: Apache Software License
Classifier: Natural Language :: English
Classifier: Operating System :: OS Independent
Classifier: Programming Language :: Python
Classifier: Programming Language :: Python :: 3 :: Only
Classifier: Programming Language :: Python :: 3.10
Classifier: Programming Language :: Python :: 3.11
Classifier: Programming Language :: Python :: 3.12
Classifier: Programming Language :: Python :: 3.13
Classifier: Programming Language :: SQL
Classifier: Topic :: Database
Classifier: Topic :: Games/Entertainment :: Role-Playing
Classifier: Topic :: Internet
Classifier: Topic :: Utilities
Requires-Python: >=3.10
License-File: LICENSE
Requires-Dist: requests
Requires-Dist: click
Requires-Dist: colorama
Requires-Dist: mwparserfromhell
Requires-Dist: lupa
Requires-Dist: pydantic
Requires-Dist: PyPika
Provides-Extra: docs
Requires-Dist: griffe-inherited-docstrings; extra == "docs"
Requires-Dist: docstring-inheritance; extra == "docs"
Requires-Dist: griffe-pydantic; extra == "docs"
Requires-Dist: griffe-generics; extra == "docs"
Requires-Dist: mkdocs-material; extra == "docs"
Requires-Dist: mkdocstrings[python]; extra == "docs"
Requires-Dist: ruff; extra == "docs"
Provides-Extra: testing
Requires-Dist: coverage; extra == "testing"
Requires-Dist: ruff; extra == "testing"
Requires-Dist: polyfactory; extra == "testing"
Provides-Extra: server
Requires-Dist: fastapi; extra == "server"
Dynamic: license-file
